{
    "title": "Beginning C++\n                        Programming - From Beginner to Beyond Obtain Modern <strong>C++</strong>\n                                Object-Oriented Programming (OOP) and STL skills. C++14 and C++17 covered. C++20 info\n                                see below. Rating: 4.6 out of 5 70669 reviews 46 total hours 305 lectures All Levels Current price: \u20b9499 Original price: \u20b93,499",
    "description": "Obtain ModernC++Object-Oriented Programming (OOP) and STL skills. C++14 and C++17 covered. C++20 info see below.",
    "instructor": "Tim Buchalka's Learn Programming\n                Academy, Dr. Frank Mitropoulos",
    "rating": "4.6",
    "reviews": "70,669",
    "total_hours": "46 total hours",
    "lectures": "305 lectures",
    "current_price": null,
    "original_price": null
}